libcore_hng/__init__.py
libcore_hng/testmodule.py
libcore_hng/configs/logger.py
libcore_hng/core/base_api_model.py
libcore_hng/core/base_app_exception.py
libcore_hng/core/base_config.py
libcore_hng/core/base_config_model.py
libcore_hng/core/base_io.py
libcore_hng/exceptions/__init__.py
libcore_hng/exceptions/api_exception.py
libcore_hng/exceptions/config_exception.py
libcore_hng/exceptions/directory_exception.py
libcore_hng/exceptions/file_exception.py
libcore_hng/exceptions/filesystem_exception.py
libcore_hng/utils/app_core.py
libcore_hng/utils/app_logger.py
libcore_hng/utils/app_logger_mixin.py
libcore_hng/utils/enums.py
libcore_hng/utils/helpers.py
libcore_hng/utils/imageops.py
libcore_hng/utils/io_manager.py
libcore_hng/utils/mathops.py
libcore_hng/utils/system.py
libcore_hng/utils/textops.py
libcore_hng/utils/thread_local_helpers.py
libcore_hng-2.0.19.dist-info/METADATA
libcore_hng-2.0.19.dist-info/WHEEL
libcore_hng-2.0.19.dist-info/top_level.txt
libcore_hng-2.0.19.dist-info/RECORD
