Metadata-Version: 2.4
Name: libcore-hng
Version: 2.0.19
Summary: A core library for scalable Python applications
Author-email: kaioman <kajin0318@gmail.com>
Project-URL: Homepage, https://github.com/kaioman/libcore-hng
Project-URL: Repository, https://github.com/kaioman/libcore-hng
Project-URL: Issues, https://github.com/kaioman/libcore-hng/issues
Requires-Dist: pydantic
Requires-Dist: psutil
Requires-Dist: pandas
Requires-Dist: openpyxl
